sshpyk/__init__.py
sshpyk/__main__.py
sshpyk/cli.py
sshpyk/get_all_specs.py
sshpyk/kernelapp.py
sshpyk/provisioning.py
sshpyk/utils.py
sshpyk/__version__.py
sshpyk-1.22.dist-info/entry_points.txt
sshpyk-1.22.dist-info/WHEEL
sshpyk-1.22.dist-info/METADATA
sshpyk-1.22.dist-info/licenses/LICENSE.txt
sshpyk-1.22.dist-info/RECORD
