Metadata-Version: 2.1
Name: sshpyk
Version: 1.22
Summary: remote jupyter kernels via ssh tunnels
License: BSD-3-Clause
Author-email: National Radio Astronomy Observatory <casa-feedback@nrao.edu>
Requires-Python: >=3.8
Classifier: Framework :: Jupyter
Classifier: Topic :: Utilities
Requires-Dist: jupyter-client>=7.0
Provides-Extra: dev
Requires-Dist: pre-commit; extra == "dev"
Project-URL: Bug Tracker, https://github.com/casangi/sshpyk/issues
Project-URL: Homepage, https://github.com/casangi/sshpyk?tab=readme-ov-file#remote-jupyter-kernels-via-ssh
Project-URL: Source, https://github.com/casangi/sshpyk
